{
  "basics": {
    "name": "Sean Taylor",
    "label": "Student",
    "picture": "https://github.com/sean-taylor2.png",
    "email": "seantayl@hawaii.edu",
    "phone": "",
    "website": "https://sean-taylor2.github.io",
    "summary": "I am studying for a B.S. in Computer Science in the Department of Information and Computer Sciences at the University of Hawaii. I expect to graduate in Spring, 2027.",
    "location": { "address": "", "postalCode": "86734", "city": "Honolulu", "countryCode": "USA", "region": "Hawaii" },
    "profiles": [
      { "network": "github", "username": "sean-taylor2", "url": "http://github.com/sean-taylor2" },
      { "network": "linkedin", "username": "sean-taylor", "url": "https://www.linkedin.com/in/sean-taylor-b7a350376" },
      { "network": "twitter", "username": "", "url": "" },
      { "network": "instagram", "username": "", "url": "" }
    ]
  },
  "interests": [
    { "name": "Software Engineering" },
    { "name": "Programming"},
    { "name": "Computer Games" },
    { "name": "Music/Art" },
  ],
  "skills": [
    {
      "name": "Languages and Frameworks",
      "keywords": [ "C", "C++", "GDScript", "Java", "Javascript"]
    },
    {
      "name": "Toolsets/OS",
      "keywords": [ "Windows 10/11", "Linux Mint", "Git/GitHub"]
    }
  ],
  "education": [
    {
      "institution": "University of Hawaii, Honolulu, HI",
      "area": "Computer Science (expected Spring, 2027)",
      "studyType": "B.S.",
      "startDate": "2022",
      "endDate": "Present",
      "courses": [
      ]
    }
  ],
  "work": [
    {
      "company": "7-Eleven",
      "position": "Sales Associate",
      "website": "",
      "startDate": "2021",
      "endDate": "2025",
      "summary": "Part time cashier / stock clerk",
      "highlights": [
        "Worked in a fast paced environment to assist customers",
        "Gained organizational skills through managing inventory"
      ]
    },
  ],
  "volunteer": [
    {
      "organization": "Moanalua High School Music Department",
      "website": "",
      "position": "Music/Field technician",
      "startDate": "2020",
      "endDate": "2024",
      "summary": "Help marching band members hone musical and technical marching skills",
      "highlights": [
        "Honed communication and leadership skills in an educational environment",
        "Built organizational skills through writing and executing lesson plans"
      ]
    }
  ],
  "references": [
    {
      "name": "Available upon request"
    }
  ]
}
